openserver/__init__.py
openserver/openserver.py
openserver-1.152.dist-info/LICENSE
openserver-1.152.dist-info/METADATA
openserver-1.152.dist-info/WHEEL
openserver-1.152.dist-info/RECORD
