Metadata-Version: 2.1
Name: openserver
Version: 1.152
Summary: Petroleum Experts OpenServer calculations
License: GNU GPL
Author: Stian Molvik
Author-email: stimo@equinor.com
Requires-Python: >=3.9,<3.13
Classifier: License :: Other/Proprietary License
Classifier: Programming Language :: Python :: 3
Classifier: Programming Language :: Python :: 3.9
Classifier: Programming Language :: Python :: 3.10
Classifier: Programming Language :: Python :: 3.11
Requires-Dist: numpy (>=1.26.1,<2.0.0)
Requires-Dist: pywin32 (>=306,<307)
